agefromname/__init__.py
agefromname/age_from_name.py
agefromname/generation_from_name.py
agefromname/regenerate_data.py
agefromname/data/mortality_table.csv.gz
agefromname/data/year_of_birth_counts.csv.gz
agefromname/test/__init__.py
agefromname/test/test_ageFromName.py
agefromname/test/test_generationFromName.py
agefromname-0.0.8.dist-info/METADATA
agefromname-0.0.8.dist-info/RECORD
agefromname-0.0.8.dist-info/WHEEL
agefromname-0.0.8.dist-info/top_level.txt
