Metadata-Version: 2.1
Name: agefromname
Version: 0.0.8
Summary: Predict how old someone is from their name and gender, using the baby name data from the US Social Security Administration. Predicts gender from name as well.
Home-page: https://github.com/JasonKessler/agefromname
Author: Jason Kessler
Author-email: jason.kessler@gmail.com
License: MIT
Platform: UNKNOWN
Requires-Dist: nose
Requires-Dist: numpy
Requires-Dist: pandas
Requires-Dist: statsmodels
Requires-Dist: beautifulsoup4
